quadipy/__init__.py
quadipy/cli.py
quadipy/schemas/__init__.py
quadipy/schemas/graph_format_config.py
quadipy/schemas/predicate_mapping.py
quadipy/schemas/quad.py
quadipy-0.2.3.dist-info/LICENSE
quadipy-0.2.3.dist-info/METADATA
quadipy-0.2.3.dist-info/WHEEL
quadipy-0.2.3.dist-info/entry_points.txt
quadipy-0.2.3.dist-info/RECORD
