Metadata-Version: 2.1
Name: quadipy
Version: 0.2.3
Summary: Package to package to transform structured data into RDF graph form
Author: Nabeel Zewail
Author-email: nabeel.zewail@vouch.us
Requires-Python: >=3.7,<4.0
Classifier: Programming Language :: Python :: 3
Classifier: Programming Language :: Python :: 3.7
Classifier: Programming Language :: Python :: 3.8
Classifier: Programming Language :: Python :: 3.9
Classifier: Programming Language :: Python :: 3.10
Classifier: Programming Language :: Python :: 3.11
Requires-Dist: click (>=8.1.0,<9.0.0)
Requires-Dist: pydantic (>=1.10.2,<2.0.0)
Requires-Dist: rdflib (>=6.2.0,<7.0.0)
